chatinterface/__init__.py
chatinterface/api.py
chatinterface/commands.py
chatinterface/helpers.py
chatinterface/interface.py
chatinterface-0.0.7.dist-info/LICENSE
chatinterface-0.0.7.dist-info/METADATA
chatinterface-0.0.7.dist-info/WHEEL
chatinterface-0.0.7.dist-info/top_level.txt
chatinterface-0.0.7.dist-info/RECORD
